torchtest/__init__.py
torchtest/torchtest.py
torchtest_shaliulab-0.0.1.dist-info/METADATA
torchtest_shaliulab-0.0.1.dist-info/WHEEL
torchtest_shaliulab-0.0.1.dist-info/entry_points.txt
torchtest_shaliulab-0.0.1.dist-info/top_level.txt
torchtest_shaliulab-0.0.1.dist-info/RECORD
