Metadata-Version: 2.1
Name: torchtest-shaliulab
Version: 0.0.1
Requires-Dist: torch
Requires-Dist: numpy
